[
    {
        "ID":1,
        "film":"Toy Story",
        "film_rating":"G",
        "cinema_score":"A",
        "release_date":"1995-11-22",
        "run_time":81,
        "budget":30000000,
        "box_office_us_canada":223225679,
        "box_office_other":171210907,
        "box_office_worldwide":394436586,
        "rotten_tomatoes_score":100,
        "rotten_tomatoes_counts":96,
        "metacritic_score":95,
        "metacritic_counts":26,
        "imdb_score":8.3,
        "imdb_counts":1089101
    },
    {
        "ID":2,
        "film":"A Bug's Life",
        "film_rating":"G",
        "cinema_score":"A",
        "release_date":"1998-11-25",
        "run_time":95,
        "budget":120000000,
        "box_office_us_canada":162798565,
        "box_office_other":200460294,
        "box_office_worldwide":363258859,
        "rotten_tomatoes_score":92,
        "rotten_tomatoes_counts":91,
        "metacritic_score":78,
        "metacritic_counts":23,
        "imdb_score":7.2,
        "imdb_counts":319596
    },
    {
        "ID":3,
        "film":"Toy Story 2",
        "film_rating":"G",
        "cinema_score":"A+",
        "release_date":"1999-11-24",
        "run_time":92,
        "budget":90000000,
        "box_office_us_canada":245852179,
        "box_office_other":265506097,
        "box_office_worldwide":511358276,
        "rotten_tomatoes_score":100,
        "rotten_tomatoes_counts":172,
        "metacritic_score":88,
        "metacritic_counts":34,
        "imdb_score":7.9,
        "imdb_counts":630573
    },
    {
        "ID":4,
        "film":"Monsters, Inc.",
        "film_rating":"G",
        "cinema_score":"A+",
        "release_date":"2001-11-02",
        "run_time":92,
        "budget":115000000,
        "box_office_us_canada":255873250,
        "box_office_other":272900000,
        "box_office_worldwide":528773250,
        "rotten_tomatoes_score":96,
        "rotten_tomatoes_counts":199,
        "metacritic_score":79,
        "metacritic_counts":35,
        "imdb_score":8.1,
        "imdb_counts":1000657
    },
    {
        "ID":5,
        "film":"Finding Nemo",
        "film_rating":"G",
        "cinema_score":"A+",
        "release_date":"2003-05-30",
        "run_time":100,
        "budget":94000000,
        "box_office_us_canada":339714978,
        "box_office_other":531300000,
        "box_office_worldwide":871014978,
        "rotten_tomatoes_score":99,
        "rotten_tomatoes_counts":270,
        "metacritic_score":90,
        "metacritic_counts":38,
        "imdb_score":8.2,
        "imdb_counts":1132877
    },
    {
        "ID":6,
        "film":"The Incredibles",
        "film_rating":"PG",
        "cinema_score":"A+",
        "release_date":"2004-11-05",
        "run_time":115,
        "budget":92000000,
        "box_office_us_canada":261441092,
        "box_office_other":370001000,
        "box_office_worldwide":631442092,
        "rotten_tomatoes_score":97,
        "rotten_tomatoes_counts":250,
        "metacritic_score":90,
        "metacritic_counts":41,
        "imdb_score":8.0,
        "imdb_counts":828986
    },
    {
        "ID":7,
        "film":"Cars",
        "film_rating":"G",
        "cinema_score":"A",
        "release_date":"2006-06-09",
        "run_time":116,
        "budget":120000000,
        "box_office_us_canada":244082982,
        "box_office_other":217900167,
        "box_office_worldwide":461983149,
        "rotten_tomatoes_score":75,
        "rotten_tomatoes_counts":204,
        "metacritic_score":73,
        "metacritic_counts":39,
        "imdb_score":7.2,
        "imdb_counts":484034
    },
    {
        "ID":8,
        "film":"Ratatouille",
        "film_rating":"G",
        "cinema_score":"A",
        "release_date":"2007-06-29",
        "run_time":111,
        "budget":150000000,
        "box_office_us_canada":206445654,
        "box_office_other":417280431,
        "box_office_worldwide":623726085,
        "rotten_tomatoes_score":96,
        "rotten_tomatoes_counts":253,
        "metacritic_score":96,
        "metacritic_counts":37,
        "imdb_score":8.1,
        "imdb_counts":851229
    },
    {
        "ID":9,
        "film":"WALL-E",
        "film_rating":"G",
        "cinema_score":"A",
        "release_date":"2008-06-27",
        "run_time":98,
        "budget":180000000,
        "box_office_us_canada":223808164,
        "box_office_other":297503696,
        "box_office_worldwide":521311860,
        "rotten_tomatoes_score":95,
        "rotten_tomatoes_counts":261,
        "metacritic_score":95,
        "metacritic_counts":39,
        "imdb_score":8.4,
        "imdb_counts":1226415
    },
    {
        "ID":10,
        "film":"Up",
        "film_rating":"PG",
        "cinema_score":"A+",
        "release_date":"2009-05-29",
        "run_time":96,
        "budget":175000000,
        "box_office_us_canada":293004164,
        "box_office_other":442094918,
        "box_office_worldwide":735099082,
        "rotten_tomatoes_score":98,
        "rotten_tomatoes_counts":297,
        "metacritic_score":88,
        "metacritic_counts":37,
        "imdb_score":8.3,
        "imdb_counts":1151249
    },
    {
        "ID":11,
        "film":"Toy Story 3",
        "film_rating":"G",
        "cinema_score":"A",
        "release_date":"2010-06-18",
        "run_time":103,
        "budget":200000000,
        "box_office_us_canada":415004880,
        "box_office_other":651964823,
        "box_office_worldwide":1066969703,
        "rotten_tomatoes_score":98,
        "rotten_tomatoes_counts":313,
        "metacritic_score":92,
        "metacritic_counts":39,
        "imdb_score":8.3,
        "imdb_counts":908222
    },
    {
        "ID":12,
        "film":"Cars 2",
        "film_rating":"G",
        "cinema_score":"A-",
        "release_date":"2011-06-24",
        "run_time":106,
        "budget":200000000,
        "box_office_us_canada":191452396,
        "box_office_other":368400000,
        "box_office_worldwide":559852396,
        "rotten_tomatoes_score":40,
        "rotten_tomatoes_counts":220,
        "metacritic_score":57,
        "metacritic_counts":38,
        "imdb_score":6.2,
        "imdb_counts":225724
    },
    {
        "ID":13,
        "film":"Brave",
        "film_rating":"PG",
        "cinema_score":"A",
        "release_date":"2012-06-22",
        "run_time":93,
        "budget":185000000,
        "box_office_us_canada":237283207,
        "box_office_other":301700000,
        "box_office_worldwide":538983207,
        "rotten_tomatoes_score":79,
        "rotten_tomatoes_counts":256,
        "metacritic_score":69,
        "metacritic_counts":37,
        "imdb_score":7.1,
        "imdb_counts":452012
    },
    {
        "ID":14,
        "film":"Monsters University",
        "film_rating":"G",
        "cinema_score":"A",
        "release_date":"2013-06-21",
        "run_time":104,
        "budget":200000000,
        "box_office_us_canada":268492764,
        "box_office_other":475066843,
        "box_office_worldwide":743559607,
        "rotten_tomatoes_score":80,
        "rotten_tomatoes_counts":203,
        "metacritic_score":65,
        "metacritic_counts":41,
        "imdb_score":7.2,
        "imdb_counts":398903
    },
    {
        "ID":15,
        "film":"Inside Out",
        "film_rating":"PG",
        "cinema_score":"A",
        "release_date":"2015-06-19",
        "run_time":95,
        "budget":175000000,
        "box_office_us_canada":356461711,
        "box_office_other":501149463,
        "box_office_worldwide":857611174,
        "rotten_tomatoes_score":98,
        "rotten_tomatoes_counts":387,
        "metacritic_score":94,
        "metacritic_counts":55,
        "imdb_score":8.1,
        "imdb_counts":834268
    },
    {
        "ID":16,
        "film":"The Good Dinosaur",
        "film_rating":"PG",
        "cinema_score":"A",
        "release_date":"2015-11-25",
        "run_time":93,
        "budget":175000000,
        "box_office_us_canada":123087120,
        "box_office_other":209120551,
        "box_office_worldwide":332207671,
        "rotten_tomatoes_score":75,
        "rotten_tomatoes_counts":220,
        "metacritic_score":66,
        "metacritic_counts":37,
        "imdb_score":6.7,
        "imdb_counts":130324
    },
    {
        "ID":17,
        "film":"Finding Dory",
        "film_rating":"PG",
        "cinema_score":"A",
        "release_date":"2016-06-17",
        "run_time":97,
        "budget":200000000,
        "box_office_us_canada":486295561,
        "box_office_other":542275328,
        "box_office_worldwide":1028570889,
        "rotten_tomatoes_score":94,
        "rotten_tomatoes_counts":339,
        "metacritic_score":77,
        "metacritic_counts":48,
        "imdb_score":7.2,
        "imdb_counts":311793
    },
    {
        "ID":18,
        "film":"Cars 3",
        "film_rating":"G",
        "cinema_score":"A",
        "release_date":"2017-06-16",
        "run_time":102,
        "budget":175000000,
        "box_office_us_canada":152901115,
        "box_office_other":231029541,
        "box_office_worldwide":383930656,
        "rotten_tomatoes_score":69,
        "rotten_tomatoes_counts":234,
        "metacritic_score":59,
        "metacritic_counts":41,
        "imdb_score":6.7,
        "imdb_counts":128849
    },
    {
        "ID":19,
        "film":"Coco",
        "film_rating":"PG",
        "cinema_score":"A+",
        "release_date":"2017-11-22",
        "run_time":105,
        "budget":175000000,
        "box_office_us_canada":210460015,
        "box_office_other":604181157,
        "box_office_worldwide":814641172,
        "rotten_tomatoes_score":97,
        "rotten_tomatoes_counts":357,
        "metacritic_score":81,
        "metacritic_counts":48,
        "imdb_score":8.4,
        "imdb_counts":618005
    },
    {
        "ID":20,
        "film":"Incredibles 2",
        "film_rating":"PG",
        "cinema_score":"A+",
        "release_date":"2018-06-15",
        "run_time":118,
        "budget":200000000,
        "box_office_us_canada":608581744,
        "box_office_other":634223615,
        "box_office_worldwide":1242805359,
        "rotten_tomatoes_score":93,
        "rotten_tomatoes_counts":390,
        "metacritic_score":80,
        "metacritic_counts":51,
        "imdb_score":7.5,
        "imdb_counts":341353
    },
    {
        "ID":21,
        "film":"Toy Story 4",
        "film_rating":"G",
        "cinema_score":"A",
        "release_date":"2019-06-21",
        "run_time":100,
        "budget":200000000,
        "box_office_us_canada":434038008,
        "box_office_other":639356585,
        "box_office_worldwide":1073394593,
        "rotten_tomatoes_score":97,
        "rotten_tomatoes_counts":459,
        "metacritic_score":84,
        "metacritic_counts":57,
        "imdb_score":7.6,
        "imdb_counts":288783
    },
    {
        "ID":22,
        "film":"Onward",
        "film_rating":"PG",
        "cinema_score":"A-",
        "release_date":"2020-03-06",
        "run_time":102,
        "budget":175000000,
        "box_office_us_canada":61555145,
        "box_office_other":80384897,
        "box_office_worldwide":141940042,
        "rotten_tomatoes_score":88,
        "rotten_tomatoes_counts":350,
        "metacritic_score":64,
        "metacritic_counts":56,
        "imdb_score":7.4,
        "imdb_counts":174917
    },
    {
        "ID":23,
        "film":"Soul",
        "film_rating":"PG",
        "cinema_score":null,
        "release_date":"2020-12-25",
        "run_time":100,
        "budget":150000000,
        "box_office_us_canada":946154,
        "box_office_other":120957731,
        "box_office_worldwide":121903885,
        "rotten_tomatoes_score":95,
        "rotten_tomatoes_counts":360,
        "metacritic_score":83,
        "metacritic_counts":55,
        "imdb_score":8.0,
        "imdb_counts":392783
    },
    {
        "ID":24,
        "film":"Luca",
        "film_rating":"PG",
        "cinema_score":null,
        "release_date":"2021-06-18",
        "run_time":95,
        "budget":0,
        "box_office_us_canada":1324302,
        "box_office_other":49788012,
        "box_office_worldwide":51112314,
        "rotten_tomatoes_score":91,
        "rotten_tomatoes_counts":303,
        "metacritic_score":71,
        "metacritic_counts":52,
        "imdb_score":7.4,
        "imdb_counts":202404
    },
    {
        "ID":25,
        "film":"Turning Red",
        "film_rating":"PG",
        "cinema_score":null,
        "release_date":"2022-03-11",
        "run_time":100,
        "budget":175000000,
        "box_office_us_canada":1399001,
        "box_office_other":20414357,
        "box_office_worldwide":21813358,
        "rotten_tomatoes_score":95,
        "rotten_tomatoes_counts":289,
        "metacritic_score":83,
        "metacritic_counts":52,
        "imdb_score":7.0,
        "imdb_counts":158649
    },
    {
        "ID":26,
        "film":"Lightyear",
        "film_rating":"PG",
        "cinema_score":"A-",
        "release_date":"2022-06-17",
        "run_time":105,
        "budget":200000000,
        "box_office_us_canada":118307188,
        "box_office_other":108118232,
        "box_office_worldwide":226425420,
        "rotten_tomatoes_score":74,
        "rotten_tomatoes_counts":319,
        "metacritic_score":60,
        "metacritic_counts":57,
        "imdb_score":6.1,
        "imdb_counts":127045
    },
    {
        "ID":27,
        "film":"Elemental",
        "film_rating":"PG",
        "cinema_score":"A",
        "release_date":"2023-06-16",
        "run_time":101,
        "budget":200000000,
        "box_office_us_canada":154426697,
        "box_office_other":342017611,
        "box_office_worldwide":496444308,
        "rotten_tomatoes_score":73,
        "rotten_tomatoes_counts":262,
        "metacritic_score":58,
        "metacritic_counts":45,
        "imdb_score":7.0,
        "imdb_counts":140174
    },
    {
        "ID":28,
        "film":"Inside Out 2",
        "film_rating":"PG",
        "cinema_score":"A",
        "release_date":"2024-06-14",
        "run_time":96,
        "budget":200000000,
        "box_office_us_canada":652980194,
        "box_office_other":1045050771,
        "box_office_worldwide":1698030965,
        "rotten_tomatoes_score":90,
        "rotten_tomatoes_counts":313,
        "metacritic_score":73,
        "metacritic_counts":59,
        "imdb_score":7.6,
        "imdb_counts":168090
    }
]